search_analysis/__init__.py
search_analysis/tools/__init__.py
search_analysis-0.1.23.dist-info/AUTHORS.rst
search_analysis-0.1.23.dist-info/LICENSE
search_analysis-0.1.23.dist-info/METADATA
search_analysis-0.1.23.dist-info/WHEEL
search_analysis-0.1.23.dist-info/top_level.txt
search_analysis-0.1.23.dist-info/RECORD
