Metadata-Version: 2.1
Name: search_analysis
Version: 0.1.23
Summary: The search analysis library contains multiple tools to help you analyze ranking and explain ranking differences from search systems.
Home-page: https://github.com/pragmalingu/search-analysis
Author: PragmaLingu
Author-email: info@pragmalingu.de
License: MIT license
Keywords: search_analysis
Platform: UNKNOWN
Classifier: Development Status :: 2 - Pre-Alpha
Classifier: Intended Audience :: Developers
Classifier: License :: OSI Approved :: MIT License
Classifier: Natural Language :: English
Classifier: Programming Language :: Python :: 3
Classifier: Programming Language :: Python :: 3.5
Classifier: Programming Language :: Python :: 3.6
Classifier: Programming Language :: Python :: 3.7
Classifier: Programming Language :: Python :: 3.8
Classifier: Programming Language :: Python :: 3.9
Requires-Python: >=3.5
License-File: LICENSE
License-File: AUTHORS.rst
